setup.py
cloudfront_log_parser/__init__.py
cloudfront_log_parser/version.py
cloudfront_log_parser.egg-info/PKG-INFO
cloudfront_log_parser.egg-info/SOURCES.txt
cloudfront_log_parser.egg-info/dependency_links.txt
cloudfront_log_parser.egg-info/entry_points.txt
cloudfront_log_parser.egg-info/requires.txt
cloudfront_log_parser.egg-info/top_level.txt
tests/__init__.py
tests/base.py
tests/fixtures.py
tests/performance.py
tests/test_parse_lines.py
tests/test_version.py