Metadata-Version: 1.1
Name: cloudfront-log-parser
Version: 0.3.0
Summary: Parse cloudfront access log lines with some extra intelligence.
Home-page: https://github.com/heynemann/cloudfront-log-parser
Author: Bernardo Heynemann
Author-email: heynemann@gmail.com
License: MIT
Keywords: cloudfront amazon aws log access parse python
Platform: UNKNOWN
Classifier: Development Status :: 4 - Beta
Classifier: Intended Audience :: Developers
Classifier: License :: OSI Approved :: MIT License
Classifier: Natural Language :: English
Classifier: Operating System :: Unix
Classifier: Programming Language :: Python :: 2.7
Classifier: Programming Language :: Python :: 3.4
Classifier: Programming Language :: Python :: Implementation :: PyPy
Classifier: Operating System :: OS Independent
